convertstruct.py
curie2dtovampire.py
exchange_generator.py
magnetic_struct_analyzer.py
mc_class.py
run_CurieD.py
magtrans-1.0.data/scripts/MagTrans
magtrans-1.0.dist-info/METADATA
magtrans-1.0.dist-info/WHEEL
magtrans-1.0.dist-info/top_level.txt
magtrans-1.0.dist-info/RECORD
