Metadata-Version: 2.1
Name: magtrans
Version: 1.0
Summary: MagTrans: Magnetic Transition Estimator
Home-page: https://github.com/gmp007/MagTrans
Author: Chinedu Ekuma
Author-email: cekuma1@gmail.com, che218@lehigh.edu
License: MIT
Requires-Dist: numpy >=1.20.0
Requires-Dist: matplotlib >=3.8.0
Requires-Dist: pymatgen >=2023.10.11
Requires-Dist: custodian >=2023.10.11
Requires-Dist: ase >=3.22.1
Requires-Dist: sympy >=1.8
Requires-Dist: numba >=0.56.4
